zat/__init__.py
zat/data_generator.py
zat/dataframe_cache.py
zat/dataframe_stats.py
zat/dataframe_to_matrix.py
zat/json_log_to_dataframe.py
zat/live_simulator.py
zat/log_to_dataframe.py
zat/log_to_sparkdf.py
zat/zeek_log_reader.py
zat/zeek_multi_log_reader.py
zat/test_data/g_test_data.csv
zat/utils/__init__.py
zat/utils/cache.py
zat/utils/dir_watcher.py
zat/utils/file_storage.py
zat/utils/file_tailer.py
zat/utils/file_utils.py
zat/utils/geo_lookup.py
zat/utils/net_utils.py
zat/utils/ngrams.py
zat/utils/plot_utils.py
zat/utils/reverse_dns.py
zat/utils/signal_utils.py
zat/utils/vt_query.py
zat-0.4.7.data/data/data/app_stats.log
zat-0.4.7.data/data/data/conn.log
zat-0.4.7.data/data/data/conn_date_issue.log
zat-0.4.7.data/data/data/dhcp.log
zat-0.4.7.data/data/data/dhcp.log.gz
zat-0.4.7.data/data/data/dhcp_002.log
zat-0.4.7.data/data/data/dhcp_002.log.gz
zat-0.4.7.data/data/data/dns.log
zat-0.4.7.data/data/data/files.log
zat-0.4.7.data/data/data/ftp.log
zat-0.4.7.data/data/data/http.log
zat-0.4.7.data/data/data/http.log.corrupt.gz
zat-0.4.7.data/data/data/http.log.gz
zat-0.4.7.data/data/data/http_empty.log
zat-0.4.7.data/data/data/intel_example.intel
zat-0.4.7.data/data/data/notice.log
zat-0.4.7.data/data/data/smtp.log
zat-0.4.7.data/data/data/ssl.log
zat-0.4.7.data/data/data/top_domains_1k.csv
zat-0.4.7.data/data/data/tor_ssl.log
zat-0.4.7.data/data/data/weird.log
zat-0.4.7.data/data/data/x509.log
zat-0.4.7.data/data/data/json/capture_loss.log
zat-0.4.7.data/data/data/json/conn.log
zat-0.4.7.data/data/data/json/dce_rpc.log
zat-0.4.7.data/data/data/json/dhcp.log
zat-0.4.7.data/data/data/json/dns.log
zat-0.4.7.data/data/data/json/files.log
zat-0.4.7.data/data/data/json/http.log
zat-0.4.7.data/data/data/json/kerberos.log
zat-0.4.7.data/data/data/json/loaded_scripts.log
zat-0.4.7.data/data/data/json/ntp.log
zat-0.4.7.data/data/data/json/packet_filter.log
zat-0.4.7.data/data/data/json/smb_files.log
zat-0.4.7.data/data/data/json/smb_mapping.log
zat-0.4.7.dist-info/LICENSE
zat-0.4.7.dist-info/METADATA
zat-0.4.7.dist-info/WHEEL
zat-0.4.7.dist-info/top_level.txt
zat-0.4.7.dist-info/RECORD
