Metadata-Version: 2.1
Name: zat
Version: 0.4.7
Summary: Zeek Analysis Tools
Home-page: https://github.com/SuperCowPowers/zat
Author: Brian Wylie
Author-email: support@supercowpowers.com
License: Apache
Keywords: Zeek,Bro,Python,Networking,Security,Scikit-Learn,Spark,Kafka,Parquet
Classifier: Development Status :: 2 - Pre-Alpha
Classifier: Intended Audience :: Developers
Classifier: License :: OSI Approved :: Apache Software License
Classifier: Natural Language :: English
Classifier: Programming Language :: Python :: 3.6
Classifier: Programming Language :: Python :: 3.7
Classifier: Programming Language :: Python :: 3.8
Classifier: Programming Language :: Python :: Implementation :: CPython
Classifier: Programming Language :: Python :: Implementation :: PyPy
License-File: LICENSE
Requires-Dist: requests
Requires-Dist: watchdog
Requires-Dist: pandas
Requires-Dist: scikit-learn
Provides-Extra: all
Requires-Dist: pyspark ; extra == 'all'
Requires-Dist: pyarrow ; extra == 'all'
Requires-Dist: yara-python ; extra == 'all'
Requires-Dist: tldextract ; extra == 'all'
Provides-Extra: pyspark
Requires-Dist: pyspark ; extra == 'pyspark'
